LICENSE.md
README.md
setup.cfg
setup.py
phdu/__init__.py
phdu/_helper.py
phdu/analysis.py
phdu/clustering.py
phdu/decomposition.py
phdu/geometry.py
phdu/integration.py
phdu/np_utils.py
phdu/pd_utils.py
phdu/script_fmt.py
phdu/storage.py
phdu.egg-info/PKG-INFO
phdu.egg-info/SOURCES.txt
phdu.egg-info/dependency_links.txt
phdu.egg-info/requires.txt
phdu.egg-info/top_level.txt
phdu/plots/__init__.py
phdu/plots/_mpl.py
phdu/plots/base.py
phdu/plots/plotly_utils.py
phdu/stats/__init__.py
phdu/stats/_integration.py
phdu/stats/_plots.py
phdu/stats/_preprocess.py
phdu/stats/bootstrap.py
phdu/stats/conf_interval.py
phdu/stats/corr.py
phdu/stats/rtopy/__init__.py
phdu/stats/rtopy/_helper.py
phdu/stats/rtopy/resample.py
phdu/stats/test/__init__.py
phdu/stats/test/_adherence.py
phdu/stats/test/multiple_comp.py
phdu/stats/test/permutation.py