Metadata-Version: 2.1
Name: phdu
Version: 3.0.5
Summary: Automatically store/load data in a tidy, efficient way. Includes functions for data visualization and analysis.
Home-page: https://github.com/medinajorge/PhD-utils
Download-URL: https://github.com/medinajorge/PhD-utils/archive/refs/tags/v2.6.7.tar.gz
Author: Jorge Medina Hernández
Author-email: medinahdezjorge@gmail.com
Keywords: science,statistics,tidy,project organization,project,organization,path,storage
Classifier: Programming Language :: Python :: 3
Classifier: Development Status :: 5 - Production/Stable
Classifier: License :: OSI Approved :: GNU Affero General Public License v3
Classifier: Operating System :: OS Independent
Classifier: Topic :: Scientific/Engineering
Classifier: Topic :: Office/Business
Classifier: Intended Audience :: Science/Research
Requires-Python: >=3
Provides-Extra: all
Provides-Extra: basic
Provides-Extra: matplotlib
Provides-Extra: plotly
Provides-Extra: colorlover
Provides-Extra: statsmodels
Provides-Extra: r
Provides-Extra: sklearn
License-File: LICENSE.md
